fzseries_api/__init__.py
fzseries_api/__main__.py
fzseries_api/console.py
fzseries_api/exceptions.py
fzseries_api/filters.py
fzseries_api/handlers.py
fzseries_api/hunter.py
fzseries_api/main.py
fzseries_api/models.py
fzseries_api/utils.py
fzseries_api-0.0.4.dist-info/LICENSE
fzseries_api-0.0.4.dist-info/METADATA
fzseries_api-0.0.4.dist-info/WHEEL
fzseries_api-0.0.4.dist-info/entry_points.txt
fzseries_api-0.0.4.dist-info/top_level.txt
fzseries_api-0.0.4.dist-info/RECORD
