Metadata-Version: 2.1
Name: fzseries-api
Version: 0.0.4
Summary: Unofficial Python SDK/API for fztvseries.live
Home-page: https://github.com/Simatwa/fzseries-api
Author: Smartwa
Author-email: simatwacaleb@proton.me
Maintainer: Smartwa
License: GPLv3
Project-URL: Bug Report, https://github.com/Simatwa/fzseries-api/issues/new
Project-URL: Homepage, https://github.com/Simatwa/fzseries-api
Project-URL: Source Code, https://github.com/Simatwa/fzseries-api
Project-URL: Issue Tracker, https://github.com/Simatwa/fzseries-api/issues
Project-URL: Download, https://github.com/Simatwa/fzseries-api/releases
Project-URL: Documentation, https://github.com/Simatwa/fzseries-api/
Keywords: series,fzseries,fztvseries,mobiletvshows
Classifier: License :: OSI Approved :: GNU General Public License v3 (GPLv3)
Classifier: Intended Audience :: Developers
Classifier: Intended Audience :: Developers
Classifier: Natural Language :: English
Classifier: License :: Free For Home Use
Classifier: Intended Audience :: Customer Service
Classifier: Programming Language :: Python
Classifier: Topic :: Software Development :: Libraries :: Python Modules
Classifier: Programming Language :: Python :: 3 :: Only
Classifier: Programming Language :: Python :: 3.10
Classifier: Programming Language :: Python :: 3.10
Classifier: Programming Language :: Python :: 3.11
Classifier: Programming Language :: Python :: 3.12
Classifier: Programming Language :: Python :: 3.13
Requires-Python: >=3.10
License-File: LICENSE
Requires-Dist: requests[socks] >=2.32.3
Requires-Dist: bs4 ==0.0.1
Requires-Dist: pydantic ==2.9.2
Requires-Dist: tqdm ==4.66.3
Requires-Dist: brotli ==1.1.0
Provides-Extra: all
Requires-Dist: click ==8.1.3 ; extra == 'all'
Requires-Dist: rich ==13.9.2 ; extra == 'all'
Provides-Extra: cli
Requires-Dist: click ==8.1.3 ; extra == 'cli'
Requires-Dist: rich ==13.9.2 ; extra == 'cli'
